Workbook

Sheet README
A1: UCG Platform - Stress Test Feedback (Nate)
A2: Companion to docs/plans/2026-08-19-uat-stress-test-plan.md
A4: HOW TO USE THIS FILE
A5: 1. Go to the Findings tab. Every step from the plan is already there, in order.
A6: 2. Fill in the Result column for EVERY step - including the ones that pass.
A7: A PASS row takes two seconds and is what makes the untested gaps visible.
A8: 3. Only fill the rest of the row when it is NOT a plain PASS.
A9: 4. Anything BROKEN: file it in-app first (Report a problem), THEN add the row here.
A10: The in-app widget captures the console-error buffer, which is overwritten as you
A11: keep clicking. Start that description with the Finding ID and your initials.
A12: 5. Blank rows at the bottom of Findings are for anything not tied to a step.
A13: 6. Answer the Decisions tab whenever you like - no testing needed for those.
... A47: PROGRESS
A48: Steps in the plan | B48: =COUNTIF(Findings!A3:A2000,"?-??")
A49: Steps with a Result filled in | B49: =COUNTIFS(Findings!A3:A2000,"?-??",Findings!D3:D2000,"<>")
A50: Still to do | B50: =COUNTIF(Findings!A3:A2000,"?-??")-COUNTIFS(Findings!A3:A2000,"?-??",Findings!D3:D2000,"<>")
A52: PASS | B52: =COUNTIF(Findings!D3:D2000,"PASS")
A53: FAIL | B53: =COUNTIF(Findings!D3:D2000,"FAIL")
A54: MISSING | B54: =COUNTIF(Findings!D3:D2000,"MISSING")
A55: UNCLEAR | B55: =COUNTIF(Findings!D3:D2000,"UNCLEAR")
A56: BLOCKED | B56: =COUNTIF(Findings!D3:D2000,"BLOCKED")
A58: S1 blockers | B58: =COUNTIF(Findings!F3:F2000,"S1")
A59: S2 major | B59: =COUNTIF(Findings!F3:F2000,"S2")
A60: Decisions raised (D) | B60: =COUNTIF(Findings!F3:F2000,"D")

Sheet Findings
A1: Step ID | B1: Lane | C1: Step (what to do) | D1: Result | E1: Finding ID | F1: Severity | G1: What you expected | H1: What actually happened (exact error text) | I1: Timestamp (local + tz) | J1: Hard reload fix it? | K1: Device / browser | L1: Signed in as | M1: Screenshot(s) | N1: Reported in-app? | O1: Notes
A2: M-07 | B2: =IFERROR(LEFT(A2,FIND("-",A2)-1),"") | C2: EXAMPLE ROW - delete or overwrite me | D2: FAIL | E2: M-07-01 | F2: S1 | G2: 3-D Secure challenge appears, then the payment completes | H2: Challenge appeared, I approved it, then "Something went wrong" and the cart still had the item | I2: 2026-08-19 14:32 PT | J2: N | K2: Win 11 / Chrome 141 | L2: Athlete (ZZTEST-Robin) | M2: M-07-01_01_JB.png, M-07-01_02_JB.png | N2: Y | O2: Reproduced twice. Stripe dashboard shows no payment attempt at all.
A3: A - Accounts, auth & security
A4: A-01 | B4: =IFERROR(LEFT(A4,FIND("-",A4)-1),"") | C4: Sign up a brand-new account from scratch
A5: A-02 | B5: =IFERROR(LEFT(A5,FIND("-",A5)-1),"") | C5: Signed out: go directly to #/admin/league
A6: A-03 | B6: =IFERROR(LEFT(A6,FIND("-",A6)-1),"") | C6: Role-less athlete: try the 3 admin routes (watch for a flash of real UI)
A7: A-04 | B7: =IFERROR(LEFT(A7,FIND("-",A7)-1),"") | C7: Refresh 3x while on an admin page as admin (no access-denied flash)
A8: A-05 | B8: =IFERROR(LEFT(A8,FIND("-",A8)-1),"") | C8: Sign out, then press browser Back
A9: A-06 | B9: =IFERROR(LEFT(A9,FIND("-",A9)-1),"") | C9: Forgot-password flow end to end
A10: A-07 | B10: =IFERROR(LEFT(A10,FIND("-",A10)-1),"") | C10: Admin sends an account invite; recipient sets a password
A11: A-08 | B11: =IFERROR(LEFT(A11,FIND("-",A11)-1),"") | C11: Enroll TOTP with a real authenticator app
A12: A-09 | B12: =IFERROR(LEFT(A12,FIND("-",A12)-1),"") | C12: Sign out, sign back in with TOTP (wrong code, then right)
A13: A-10 | B13: =IFERROR(LEFT(A13,FIND("-",A13)-1),"") | C13: Enroll a passkey on real hardware; sign in with it
A14: A-11 | B14: =IFERROR(LEFT(A14,FIND("-",A14)-1),"") | C14: Sign in as an admin with no MFA enrolled (the nag)
A15: A-12 | B15: =IFERROR(LEFT(A15,FIND("-",A15)-1),"") | C15: Nate: admin MFA reset break-glass
... A17: A-14 | B17: =IFERROR(LEFT(A17,FIND("-",A17)-1),"") | C17: Signed in on phone + desktop; change name on one
A18: M - Cart, pricing & Stripe checkout
A19: M-01 | B19: =IFERROR(LEFT(A19,FIND("-",A19)-1),"") | C19: Add one registration to cart; write down every number
A20: M-02 | B20: =IFERROR(LEFT(A20,FIND("-",A20)-1),"") | C20: Compare the Stripe page's numbers against the cart, to the cent
A21: M-03 | B21: =IFERROR(LEFT(A21,FIND("-",A21)-1),"") | C21: Pay with 4242; watch what happens after
A22: M-04 | B22: =IFERROR(LEFT(A22,FIND("-",A22)-1),"") | C22: Confirmation email vs the in-app receipt
A23: M-05 | B23: =IFERROR(LEFT(A23,FIND("-",A23)-1),"") | C23: Open the receipt PDF and actually print it
A24: M-06 | B24: =IFERROR(LEFT(A24,FIND("-",A24)-1),"") | C24: Checkout with the DECLINE card 4000...0002
A25: M-07 | B25: =IFERROR(LEFT(A25,FIND("-",A25)-1),"") | C25: Checkout with the 3-D SECURE card 4000 0025 0000 3155
A26: M-08 | B26: =IFERROR(LEFT(A26,FIND("-",A26)-1),"") | C26: Start a checkout and abandon it (close the tab mid-payment)
A27: M-09 | B27: =IFERROR(LEFT(A27,FIND("-",A27)-1),"") | C27: Browser Back button from inside Stripe checkout
A28: M-10 | B28: =IFERROR(LEFT(A28,FIND("-",A28)-1),"") | C28: Cart with registration + add-ons + a change fee together
A29: M-11 | B29: =IFERROR(LEFT(A29,FIND("-",A29)-1),"") | C29: Apply a promo/coupon code (visible in cart AND in Stripe)
A30: M-12 | B30: =IFERROR(LEFT(A30,FIND("-",A30)-1),"") | C30: Coupon that covers 100% of the total
... A38: M-20 | B38: =IFERROR(LEFT(A38,FIND("-",A38)-1),"") | C38: #/me/purchases vs the Stripe Dashboard test payments
A39: Z - Two-person concurrency (JOINT)
A40: Z-01 | B40: =IFERROR(LEFT(A40,FIND("-",A40)-1),"") | C40: SIMULTANEOUS CHECKOUT x3 - record BOTH invoice numbers verbatim
A41: Z-02 | B41: =IFERROR(LEFT(A41,FIND("-",A41)-1),"") | C41: Both register the SAME athlete for the SAME event at once
A42: Z-03 | B42: =IFERROR(LEFT(A42,FIND("-",A42)-1),"") | C42: Both fill the last capacity slots at once
A43: Z-04 | B43: =IFERROR(LEFT(A43,FIND("-",A43)-1),"") | C43: Both approve the SAME refund request at once
A44: Z-05 | B44: =IFERROR(LEFT(A44,FIND("-",A44)-1),"") | C44: Both save different changes to the same event settings
A45: Z-06 | B45: =IFERROR(LEFT(A45,FIND("-",A45)-1),"") | C45: Both enter a different score for the same athlete/apparatus
A46: E - Email & SMS deliverability
A47: E-01 | B47: =IFERROR(LEFT(A47,FIND("-",A47)-1),"") | C47: Trigger all 13 transactional emails; check arrival/spam/from/reply-to/phone
A48: E-02 | B48: =IFERROR(LEFT(A48,FIND("-",A48)-1),"") | C48: Per-event custom confirmation email body
A49: E-03 | B49: =IFERROR(LEFT(A49,FIND("-",A49)-1),"") | C49: Event from-alias + reply-to (hit Reply and see where it goes)
A50: E-04 | B50: =IFERROR(LEFT(A50,FIND("-",A50)-1),"") | C50: CC the director on a confirmation
A51: E-05 | B51: =IFERROR(LEFT(A51,FIND("-",A51)-1),"") | C51: Admin Communicate: email a filtered group
A52: E-06 | B52: =IFERROR(LEFT(A52,FIND("-",A52)-1),"") | C52: Admin Communicate: test send
A53: E-07 | B53: =IFERROR(LEFT(A53,FIND("-",A53)-1),"") | C53: Event Communicate as a HOST (email yes, SMS admin-only by design)
A54: E-08 | B54: =IFERROR(LEFT(A54,FIND("-",A54)-1),"") | C54: Event Communicate: filter by session / level / discipline
A55: E-09 | B55: =IFERROR(LEFT(A55,FIND("-",A55)-1),"") | C55: Send an SMS to yourself; reply to it
A56: E-10 | B56: =IFERROR(LEFT(A56,FIND("-",A56)-1),"") | C56: Reply STOP, then try to send again
A57: E-11 | B57: =IFERROR(LEFT(A57,FIND("-",A57)-1),"") | C57: Sent log after the email and SMS sends
A58: E-12 | B58: =IFERROR(LEFT(A58,FIND("-",A58)-1),"") | C58: Open the 3 most important emails on a PHONE
A59: E-13 | B59: =IFERROR(LEFT(A59,FIND("-",A59)-1),"") | C59: Did anything land in spam or Promotions?
A60: G - Athlete self-service registration
A61: G-01 | B61: =IFERROR(LEFT(A61,FIND("-",A61)-1),"") | C61: Non-member tries to register (season-targeted membership link?)
A62: G-02 | B62: =IFERROR(LEFT(A62,FIND("-",A62)-1),"") | C62: Buy the membership through that link, return, register
A63: G-03 | B63: =IFERROR(LEFT(A63,FIND("-",A63)-1),"") | C63: Register while signed out (does it return you to the event?)
A64: G-04 | B64: =IFERROR(LEFT(A64,FIND("-",A64)-1),"") | C64: Registration popup: disciplines, level, apparatus, all-around
A65: G-05 | B65: =IFERROR(LEFT(A65,FIND("-",A65)-1),"") | C65: T&T: multiple disciplines with per-apparatus levels
A66: G-06 | B66: =IFERROR(LEFT(A66,FIND("-",A66)-1),"") | C66: T&T: try to remove your LAST remaining discipline
A67: G-07 | B67: =IFERROR(LEFT(A67,FIND("-",A67)-1),"") | C67: Synchro: pick a partner from the member list
A68: G-08 | B68: =IFERROR(LEFT(A68,FIND("-",A68)-1),"") | C68: Have your partner pick someone else (jilted-athlete email?)
A69: G-09 | B69: =IFERROR(LEFT(A69,FIND("-",A69)-1),"") | C69: Add-ons in the popup: banquet / t-shirt / leo / banner
A70: G-10 | B70: =IFERROR(LEFT(A70,FIND("-",A70)-1),"") | C70: Banquet: buy 2 for yourself (max 1 ASSIGNED to you)
A71: G-11 | B71: =IFERROR(LEFT(A71,FIND("-",A71)-1),"") | C71: Survey questions come LAST, after add-ons
A72: G-12 | B72: =IFERROR(LEFT(A72,FIND("-",A72)-1),"") | C72: #/me/registrations shows everything incl. add-ons + survey
... A80: G-20 | B80: =IFERROR(LEFT(A80,FIND("-",A80)-1),"") | C80: Request a refund on one of your registrations (self-serve)
A81: W - Membership & waivers
A82: W-01 | B82: =IFERROR(LEFT(A82,FIND("-",A82)-1),"") | C82: Buy an athlete membership end to end
A83: W-02 | B83: =IFERROR(LEFT(A83,FIND("-",A83)-1),"") | C83: Buy a coach membership
A84: W-03 | B84: =IFERROR(LEFT(A84,FIND("-",A84)-1),"") | C84: Sign the waiver inline during purchase
A85: W-04 | B85: =IFERROR(LEFT(A85,FIND("-",A85)-1),"") | C85: Sign via the emailed direct link as an adult
A86: W-05 | B86: =IFERROR(LEFT(A86,FIND("-",A86)-1),"") | C86: Guardian path: minor's membership -> guardian waiver request
A87: W-06 | B87: =IFERROR(LEFT(A87,FIND("-",A87)-1),"") | C87: Try signing with the WRONG name on the direct link
A88: W-07 | B88: =IFERROR(LEFT(A88,FIND("-",A88)-1),"") | C88: Club-paying membership while the club cart is UNPAID
A89: W-08 | B89: =IFERROR(LEFT(A89,FIND("-",A89)-1),"") | C89: *** Same membership AFTER the club pays (see Appendix B) ***
A90: W-09 | B90: =IFERROR(LEFT(A90,FIND("-",A90)-1),"") | C90: Membership with BOTH a waiver hold and a club-payment hold
A91: W-10 | B91: =IFERROR(LEFT(A91,FIND("-",A91)-1),"") | C91: Admin: who signed which waiver version
A92: W-11 | B92: =IFERROR(LEFT(A92,FIND("-",A92)-1),"") | C92: Publish a new waiver version; check an existing signature
A93: W-12 | B93: =IFERROR(LEFT(A93,FIND("-",A93)-1),"") | C93: Buy a membership for a past/future season
A94: K - Camps
A95: K-01 | B95: =IFERROR(LEFT(A95,FIND("-",A95)-1),"") | C95: Register for a camp (no discipline/level/apparatus step)
A96: K-02 | B96: =IFERROR(LEFT(A96,FIND("-",A96)-1),"") | C96: Camp registration WITHOUT a club membership (should be allowed)
A97: K-03 | B97: =IFERROR(LEFT(A97,FIND("-",A97)-1),"") | C97: Camp registration WITHOUT an individual membership (should block)
A98: K-04 | B98: =IFERROR(LEFT(A98,FIND("-",A98)-1),"") | C98: Overnight survey: bedtime / noise / cabin gender / roommate
A99: K-05 | B99: =IFERROR(LEFT(A99,FIND("-",A99)-1),"") | C99: Edit the survey after registering (free, no change fee)
A100: K-06 | B100: =IFERROR(LEFT(A100,FIND("-",A100)-1),"") | C100: Camp add-ons: size required, $0 allowed, explicit 'no shirt/leo'
A101: K-07 | B101: =IFERROR(LEFT(A101,FIND("-",A101)-1),"") | C101: Camp confirmation email: survey + add-ons + edit link
A102: K-08 | B102: =IFERROR(LEFT(A102,FIND("-",A102)-1),"") | C102: Camp export: 1 line per athlete with all the spec'd columns
A103: K-09 | B103: =IFERROR(LEFT(A103,FIND("-",A103)-1),"") | C103: *** DECISION: can a club manager register athletes for a camp? ***
A104: K-10 | B104: =IFERROR(LEFT(A104,FIND("-",A104)-1),"") | C104: Edit a camp registration made before 2026-07-23 (if any exist)
A105: C - Club manager
A106: C-01 | B106: =IFERROR(LEFT(A106,FIND("-",A106)-1),"") | C106: Roster: add, edit, remove an athlete
A107: C-02 | B107: =IFERROR(LEFT(A107,FIND("-",A107)-1),"") | C107: Send a club invite; accept it from the other side
A108: C-03 | B108: =IFERROR(LEFT(A108,FIND("-",A108)-1),"") | C108: Status bubbles: Registered / In Cart / Pending Changes / Updated
A109: C-04 | B109: =IFERROR(LEFT(A109,FIND("-",A109)-1),"") | C109: Swap an athlete in an existing registration (change fee applies)
A110: C-05 | B110: =IFERROR(LEFT(A110,FIND("-",A110)-1),"") | C110: Register several athletes at once; check out as the club
A111: C-06 | B111: =IFERROR(LEFT(A111,FIND("-",A111)-1),"") | C111: Add-ons: assign banquet tickets to athletes and to EXTRA
A112: C-07 | B112: =IFERROR(LEFT(A112,FIND("-",A112)-1),"") | C112: T-shirts/leos: quantity + size PER UNIT
A113: C-08 | B113: =IFERROR(LEFT(A113,FIND("-",A113)-1),"") | C113: Club banner: 1 per club, exact-name text box
A114: C-09 | B114: =IFERROR(LEFT(A114,FIND("-",A114)-1),"") | C114: Members-without-membership card + 'last sent [date]'
A115: C-10 | B115: =IFERROR(LEFT(A115,FIND("-",A115)-1),"") | C115: 'Create new athlete' from that card
...

Sheet Decisions
A1: Decisions needed - no testing required, just your answer
A3: # | B3: Topic | C3: The question | D3: Your answer
A4: D-1 | B4: Camps and club managers | C4: Spec SS-G says camps are individual self-registration only, but a club manager can still register athletes for one. Block it outright, or keep it as a convenience?
A5: D-2 | B5: Host payout timing | C5: The 'owed' formula is settled (gross before fees, refunds not deducted). WHEN payout happens is still just wording on the host page. Is '1 week after the event' the policy?
A6: D-3 | B6: Hosts and SMS | C6: Hosts currently get email only from the event Communicate page; SMS stays league-admin-only because each text bills UCG. Still right?
A7: D-4 | B7: Invoice numbering format | C7: Two formats coexist. Which one do you want on real financial records?
A8: D-5 | B8: Refund policy edges | C8: After-deadline is 75% before processing fees. Should add-ons follow the same 75% rule, or refund in full?
A9: D-6 | B9: Anything in Appendix A you think should not wait | C9: List anything from the known-gaps appendix you want prioritized, and why.
